{"description":"Displays help text when hovering on an element.","displayName":"Poptip","methods":[],"props":{"children":{"type":{"name":"node"},"required":true,"description":"Content that, when hovered on, makes the Poptip appear"},"content":{"type":{"name":"union","value":[{"name":"node"},{"name":"string"}]},"required":false,"description":"content could be a node of a string"},"disable":{"type":{"name":"bool"},"required":false,"description":"disable value | default => false"},"position":{"type":{"name":"enum","value":[{"value":"'top'","computed":false},{"value":"'bottom'","computed":false},{"value":"'left'","computed":false},{"value":"'right'","computed":false}]},"required":false,"description":"position value options | default => top"},"theme":{"type":{"name":"string"},"required":false,"description":"background color | default => dark"},"trigger":{"type":{"name":"enum","value":[{"value":"'mouseenter'","computed":false},{"value":"'focus'","computed":false},{"value":"'click'","computed":false},{"value":"'manual'","computed":false}]},"required":false,"description":"trigger value options | default => mouseenter focus"}},"private":false}