[
    {
        "componentChunkName": "component---cache-dev-404-page-js",
        "layout": "layout---index",
        "layoutComponentChunkName": "component---src-layouts-index-js",
        "jsonName": "dev-404-page.json",
        "path": "/dev-404-page/"
    },
    {
        "componentChunkName": "component---src-pages-changelog-js",
        "layout": "layout---index",
        "layoutComponentChunkName": "component---src-layouts-index-js",
        "jsonName": "changelog.json",
        "path": "/changelog/"
    },
    {
        "componentChunkName": "component---src-pages-404-js",
        "layout": "layout---index",
        "layoutComponentChunkName": "component---src-layouts-index-js",
        "jsonName": "404.json",
        "path": "/404/"
    },
    {
        "componentChunkName": "component---src-pages-index-js",
        "layout": "layout---index",
        "layoutComponentChunkName": "component---src-layouts-index-js",
        "jsonName": "index.json",
        "path": "/"
    },
    {
        "componentChunkName": "component---src-pages-oui-js",
        "layout": "layout---index",
        "layoutComponentChunkName": "component---src-layouts-index-js",
        "jsonName": "oui.json",
        "path": "/oui/"
    },
    {
        "componentChunkName": "component---src-pages-page-2-js",
        "layout": "layout---index",
        "layoutComponentChunkName": "component---src-layouts-index-js",
        "jsonName": "page-2.json",
        "path": "/page-2/"
    },
    {
        "componentChunkName": "component---src-pages-404-js",
        "layout": "layout---index",
        "layoutComponentChunkName": "component---src-layouts-index-js",
        "jsonName": "404-html.json",
        "path": "/404.html"
    },
    {
        "componentChunkName": "component---src-pages-design-index-js",
        "layout": "layout---index",
        "layoutComponentChunkName": "component---src-layouts-index-js",
        "jsonName": "design.json",
        "path": "/design/"
    },
    {
        "componentChunkName": "component---src-pages-resources-index-js",
        "layout": "layout---index",
        "layoutComponentChunkName": "component---src-layouts-index-js",
        "jsonName": "resources.json",
        "path": "/resources/"
    },
    {
        "componentChunkName": "component---src-pages-components-arrows-inline-js",
        "layout": "layout---index",
        "layoutComponentChunkName": "component---src-layouts-index-js",
        "jsonName": "components-arrows-inline.json",
        "path": "/components/ArrowsInline/"
    },
    {
        "componentChunkName": "component---src-pages-components-accordion-js",
        "layout": "layout---index",
        "layoutComponentChunkName": "component---src-layouts-index-js",
        "jsonName": "components-accordion.json",
        "path": "/components/Accordion/"
    },
    {
        "componentChunkName": "component---src-pages-components-block-list-js",
        "layout": "layout---index",
        "layoutComponentChunkName": "component---src-layouts-index-js",
        "jsonName": "components-block-list.json",
        "path": "/components/BlockList/"
    },
    {
        "componentChunkName": "component---src-pages-components-attention-js",
        "layout": "layout---index",
        "layoutComponentChunkName": "component---src-layouts-index-js",
        "jsonName": "components-attention.json",
        "path": "/components/Attention/"
    },
    {
        "componentChunkName": "component---src-pages-components-badge-js",
        "layout": "layout---index",
        "layoutComponentChunkName": "component---src-layouts-index-js",
        "jsonName": "components-badge.json",
        "path": "/components/Badge/"
    },
    {
        "componentChunkName": "component---src-pages-components-array-js",
        "layout": "layout---index",
        "layoutComponentChunkName": "component---src-layouts-index-js",
        "jsonName": "components-array.json",
        "path": "/components/Array/"
    },
    {
        "componentChunkName": "component---src-pages-components-button-js",
        "layout": "layout---index",
        "layoutComponentChunkName": "component---src-layouts-index-js",
        "jsonName": "components-button.json",
        "path": "/components/Button/"
    },
    {
        "componentChunkName": "component---src-pages-components-button-row-js",
        "layout": "layout---index",
        "layoutComponentChunkName": "component---src-layouts-index-js",
        "jsonName": "components-button-row.json",
        "path": "/components/ButtonRow/"
    },
    {
        "componentChunkName": "component---src-pages-components-card-js",
        "layout": "layout---index",
        "layoutComponentChunkName": "component---src-layouts-index-js",
        "jsonName": "components-card.json",
        "path": "/components/Card/"
    },
    {
        "componentChunkName": "component---src-pages-components-checkbox-js",
        "layout": "layout---index",
        "layoutComponentChunkName": "component---src-layouts-index-js",
        "jsonName": "components-checkbox.json",
        "path": "/components/Checkbox/"
    },
    {
        "componentChunkName": "component---src-pages-components-code-js",
        "layout": "layout---index",
        "layoutComponentChunkName": "component---src-layouts-index-js",
        "jsonName": "components-code.json",
        "path": "/components/Code/"
    },
    {
        "componentChunkName": "component---src-pages-components-disclose-js",
        "layout": "layout---index",
        "layoutComponentChunkName": "component---src-layouts-index-js",
        "jsonName": "components-disclose.json",
        "path": "/components/Disclose/"
    },
    {
        "componentChunkName": "component---src-pages-components-dialog-js",
        "layout": "layout---index",
        "layoutComponentChunkName": "component---src-layouts-index-js",
        "jsonName": "components-dialog.json",
        "path": "/components/Dialog/"
    },
    {
        "componentChunkName": "component---src-pages-components-dropdown-js",
        "layout": "layout---index",
        "layoutComponentChunkName": "component---src-layouts-index-js",
        "jsonName": "components-dropdown.json",
        "path": "/components/Dropdown/"
    },
    {
        "componentChunkName": "component---src-pages-components-empty-dashboard-js",
        "layout": "layout---index",
        "layoutComponentChunkName": "component---src-layouts-index-js",
        "jsonName": "components-empty-dashboard.json",
        "path": "/components/EmptyDashboard/"
    },
    {
        "componentChunkName": "component---src-pages-components-help-js",
        "layout": "layout---index",
        "layoutComponentChunkName": "component---src-layouts-index-js",
        "jsonName": "components-help.json",
        "path": "/components/Help/"
    },
    {
        "componentChunkName": "component---src-pages-components-input-js",
        "layout": "layout---index",
        "layoutComponentChunkName": "component---src-layouts-index-js",
        "jsonName": "components-input.json",
        "path": "/components/Input/"
    },
    {
        "componentChunkName": "component---src-pages-components-input-icon-js",
        "layout": "layout---index",
        "layoutComponentChunkName": "component---src-layouts-index-js",
        "jsonName": "components-input-icon.json",
        "path": "/components/InputIcon/"
    },
    {
        "componentChunkName": "component---src-pages-components-label-js",
        "layout": "layout---index",
        "layoutComponentChunkName": "component---src-layouts-index-js",
        "jsonName": "components-label.json",
        "path": "/components/Label/"
    },
    {
        "componentChunkName": "component---src-pages-components-link-js",
        "layout": "layout---index",
        "layoutComponentChunkName": "component---src-layouts-index-js",
        "jsonName": "components-link.json",
        "path": "/components/Link/"
    },
    {
        "componentChunkName": "component---src-pages-components-media-js",
        "layout": "layout---index",
        "layoutComponentChunkName": "component---src-layouts-index-js",
        "jsonName": "components-media.json",
        "path": "/components/Media/"
    },
    {
        "componentChunkName": "component---src-pages-components-nav-js",
        "layout": "layout---index",
        "layoutComponentChunkName": "component---src-layouts-index-js",
        "jsonName": "components-nav.json",
        "path": "/components/Nav/"
    },
    {
        "componentChunkName": "component---src-pages-components-overlay-wrapper-js",
        "layout": "layout---index",
        "layoutComponentChunkName": "component---src-layouts-index-js",
        "jsonName": "components-overlay-wrapper.json",
        "path": "/components/OverlayWrapper/"
    },
    {
        "componentChunkName": "component---src-pages-components-pagination-js",
        "layout": "layout---index",
        "layoutComponentChunkName": "component---src-layouts-index-js",
        "jsonName": "components-pagination.json",
        "path": "/components/Pagination/"
    },
    {
        "componentChunkName": "component---src-pages-components-popover-js",
        "layout": "layout---index",
        "layoutComponentChunkName": "component---src-layouts-index-js",
        "jsonName": "components-popover.json",
        "path": "/components/Popover/"
    },
    {
        "componentChunkName": "component---src-pages-components-poptip-js",
        "layout": "layout---index",
        "layoutComponentChunkName": "component---src-layouts-index-js",
        "jsonName": "components-poptip.json",
        "path": "/components/Poptip/"
    },
    {
        "componentChunkName": "component---src-pages-components-progress-bar-js",
        "layout": "layout---index",
        "layoutComponentChunkName": "component---src-layouts-index-js",
        "jsonName": "components-progress-bar.json",
        "path": "/components/ProgressBar/"
    },
    {
        "componentChunkName": "component---src-pages-components-progress-dots-js",
        "layout": "layout---index",
        "layoutComponentChunkName": "component---src-layouts-index-js",
        "jsonName": "components-progress-dots.json",
        "path": "/components/ProgressDots/"
    },
    {
        "componentChunkName": "component---src-pages-components-radio-js",
        "layout": "layout---index",
        "layoutComponentChunkName": "component---src-layouts-index-js",
        "jsonName": "components-radio.json",
        "path": "/components/Radio/"
    },
    {
        "componentChunkName": "component---src-pages-components-search-js",
        "layout": "layout---index",
        "layoutComponentChunkName": "component---src-layouts-index-js",
        "jsonName": "components-search.json",
        "path": "/components/Search/"
    },
    {
        "componentChunkName": "component---src-pages-components-select-js",
        "layout": "layout---index",
        "layoutComponentChunkName": "component---src-layouts-index-js",
        "jsonName": "components-select.json",
        "path": "/components/Select/"
    },
    {
        "componentChunkName": "component---src-pages-components-spinner-js",
        "layout": "layout---index",
        "layoutComponentChunkName": "component---src-layouts-index-js",
        "jsonName": "components-spinner.json",
        "path": "/components/Spinner/"
    },
    {
        "componentChunkName": "component---src-pages-components-stats-js",
        "layout": "layout---index",
        "layoutComponentChunkName": "component---src-layouts-index-js",
        "jsonName": "components-stats.json",
        "path": "/components/Stats/"
    },
    {
        "componentChunkName": "component---src-pages-components-steps-js",
        "layout": "layout---index",
        "layoutComponentChunkName": "component---src-layouts-index-js",
        "jsonName": "components-steps.json",
        "path": "/components/Steps/"
    },
    {
        "componentChunkName": "component---src-pages-components-tab-nav-js",
        "layout": "layout---index",
        "layoutComponentChunkName": "component---src-layouts-index-js",
        "jsonName": "components-tab-nav.json",
        "path": "/components/TabNav/"
    },
    {
        "componentChunkName": "component---src-pages-components-table-js",
        "layout": "layout---index",
        "layoutComponentChunkName": "component---src-layouts-index-js",
        "jsonName": "components-table.json",
        "path": "/components/Table/"
    },
    {
        "componentChunkName": "component---src-pages-components-text-field-js",
        "layout": "layout---index",
        "layoutComponentChunkName": "component---src-layouts-index-js",
        "jsonName": "components-text-field.json",
        "path": "/components/TextField/"
    },
    {
        "componentChunkName": "component---src-pages-components-textarea-js",
        "layout": "layout---index",
        "layoutComponentChunkName": "component---src-layouts-index-js",
        "jsonName": "components-textarea.json",
        "path": "/components/Textarea/"
    },
    {
        "componentChunkName": "component---src-pages-components-token-js",
        "layout": "layout---index",
        "layoutComponentChunkName": "component---src-layouts-index-js",
        "jsonName": "components-token.json",
        "path": "/components/Token/"
    },
    {
        "componentChunkName": "component---src-pages-components-index-js",
        "layout": "layout---index",
        "layoutComponentChunkName": "component---src-layouts-index-js",
        "jsonName": "components.json",
        "path": "/components/"
    }
]